{
  "23": "#",
  "2f": "/",
  "-753a8e73": "/services",
  "-3a279d80": "/google-placement",
  "4b0e6111": "/contact",
  "5032f721": "/#/checkout",
  "2b59f15c": "https://cal.optimalpros.com/o/google",
  "-2523a8cb": "tel:+13143901184",
  "4654783f": "mailto:sales@optimalpros.com",
  "-41c194fe": "mailto:support@optimalpros.com",
  "1750dc24": "http://facebook.com/",
  "636eb9b8": "https://twitter.com/",
  "b979dd0": "https://www.instagram.com/",
  "-f3f4979": "https://facebook.com/",
  "2c48051": "/blog",
  "-3b71859e": "tel:13143901184",
  "273a338a": "#Open-Positions",
  "20e90869": "#read-more",
  "-6bd4518b": "/checkout",
  "4065ec19": "#Quote",
  "7f16b0b1": "https://brixtemplates.com/",
  "6bccb4d": "https://unsplash.com/",
  "675d206d": "https://www.pexels.com/",
  "-66d21c24": "https://www.freepik.com/",
  "1f3ed782": "https://unsplash.com/photos/LQZQM_z1b-s",
  "-34300c06": "https://unsplash.com/photos/FV3GConVSss",
  "-7bc14185": "https://unsplash.com/photos/xVRdDDe6M1A",
  "-7ad924c7": "https://unsplash.com/photos/9e9PD9blAto",
  "7297e479": "https://unsplash.com/photos/wawEfYdpkag",
  "-7f8e7bb2": "https://unsplash.com/photos/rRiAzFkJPMo",
  "73508f37": "https://unsplash.com/photos/vHVfpi3h5xk",
  "-1a11bdd5": "https://unsplash.com/photos/oWiEeTIxYvk",
  "-41de6f6f": "https://unsplash.com/photos/kvF6Q_i8EDI",
  "-33d5af48": "https://unsplash.com/photos/8Klz66m11hU",
  "-198f6765": "https://unsplash.com/photos/nZJBt4gQlKI",
  "52c6cb9b": "https://www.pexels.com/photo/man-in-white-polo-shirt-smiling-3785110/",
  "-6d941026": "https://www.pexels.com/photo/portrait-photo-of-woman-in-red-sweater-in-front-of-white-background-3771123/",
  "2ccafeb5": "https://www.pexels.com/photo/man-in-red-button-up-shirt-smiling-3777946/",
  "-f91b5b3": "https://www.freepik.com/free-photo/handsome-young-man-white-background_5000061.htm#page=1&query=man%20portrait&position=11",
  "-2da227e3": "https://www.freepik.com/free-photo/portrait-handsome-young-man-with-crossed-arms_9118757.htm#page=1&query=man&position=46",
  "3e93c94": "https://www.freepik.com/free-photo/young-tender-fair-haired-teenage-girl-with-healthy-skin-wearing-blue-top-looking-with-serious-pensive-expression-caucasian-woman-model-with-hands-pockets-posing-indoors_8920786.htm#page=2&query=women++blonde+woman&position=42",
  "76a31a6b": "https://university.webflow.com/",
  "-4a97dc04": "mailto:growth@brixtemplates.com",
  "2e232d8": "https://brixtemplates.com/webflow-design-agency",
  "-16a3e8df": "https://brixtemplates.com/icon-fonts",
  "-33e0f8a7": "https://brixtemplates.com/template-idea",
  "-4be23c8d": "#Colors",
  "-4fbb3e4e": "#Typography",
  "3fed00b7": "#Icons",
  "-5a9b8622": "#Buttons",
  "-19201acc": "https://webflow.com/templates/html/growth-marketing-website-template"
}